self_paced_ensemble/__init__.py
self_paced_ensemble/__version__.py
self_paced_ensemble/canonical_ensemble/__init__.py
self_paced_ensemble/canonical_ensemble/canonical_ensemble.py
self_paced_ensemble/canonical_resampling/__init__.py
self_paced_ensemble/canonical_resampling/canonical_resampling.py
self_paced_ensemble/self_paced_ensemble/__init__.py
self_paced_ensemble/self_paced_ensemble/_base_sampler.py
self_paced_ensemble/self_paced_ensemble/_self_paced_ensemble.py
self_paced_ensemble/self_paced_ensemble/_self_paced_under_sampler.py
self_paced_ensemble/self_paced_ensemble/base.py
self_paced_ensemble/utils/__init__.py
self_paced_ensemble/utils/_plot.py
self_paced_ensemble/utils/_utils.py
self_paced_ensemble/utils/_validation.py
self_paced_ensemble/utils/_validation_data.py
self_paced_ensemble/utils/_validation_param.py
self_paced_ensemble-0.1.7.dist-info/LICENSE
self_paced_ensemble-0.1.7.dist-info/METADATA
self_paced_ensemble-0.1.7.dist-info/WHEEL
self_paced_ensemble-0.1.7.dist-info/top_level.txt
self_paced_ensemble-0.1.7.dist-info/RECORD
