Metadata-Version: 2.1
Name: self-paced-ensemble
Version: 0.1.7
Summary: Self-paced Ensemble for classification on class-imbalanced data.
Home-page: https://github.com/ZhiningLiu1998/self-paced-ensemble
Author: Zhining Liu
Author-email: zhining.liu@outlook.com
License: MIT
Project-URL: Documentation, https://imbalanced-ensemble.readthedocs.io/en/latest/api/ensemble/_autosummary/imbens.ensemble.under_sampling.SelfPacedEnsembleClassifier.html
Project-URL: Source, https://github.com/ZhiningLiu1998/self-paced-ensemble
Project-URL: Tracker, https://github.com/ZhiningLiu1998/self-paced-ensemble/issues
Project-URL: Download, https://pypi.org/project/self-paced-ensemble/#files
Classifier: Intended Audience :: Science/Research
Classifier: Intended Audience :: Developers
Classifier: License :: OSI Approved
Classifier: Programming Language :: C
Classifier: Programming Language :: Python
Classifier: Topic :: Software Development
Classifier: Topic :: Scientific/Engineering
Classifier: Operating System :: Microsoft :: Windows
Classifier: Operating System :: POSIX
Classifier: Operating System :: Unix
Classifier: Operating System :: MacOS
Classifier: Programming Language :: Python :: 3.6
Classifier: Programming Language :: Python :: 3.7
Classifier: Programming Language :: Python :: 3.8
Classifier: Programming Language :: Python :: 3.9
Requires-Python: >=3.6.0
License-File: LICENSE
Requires-Dist: numpy (>=1.13.3)
Requires-Dist: pandas (>=1.1.3)
Requires-Dist: scipy (>=0.19.1)
Requires-Dist: scikit-learn (>=0.24)
Requires-Dist: joblib (>=0.11)
Requires-Dist: imbalanced-learn (>=0.12.0)
Requires-Dist: imbalanced-ensemble (>=0.2.1)
